<?xml version="1.0" encoding="UTF-8"?>
<Profile majorVersion="1" minorVersion="5" product="ATEM Mini">
    <MacroPool>
        <Macro index="0" name="Song Over" description="">
            <Op id="KeyType" mixEffectBlockIndex="0" keyIndex="0" type="Luma"/>
            <Op id="KeyFillInput" mixEffectBlockIndex="0" keyIndex="0" input="Camera4"/>
            <Op id="KeyCutInput" mixEffectBlockIndex="0" keyIndex="0" input="Black"/>
            <Op id="LumaKeyPreMultiply" mixEffectBlockIndex="0" keyIndex="0" preMultiply="True"/>
            <Op id="DVEKeyMaskEnable" mixEffectBlockIndex="0" keyIndex="0" enable="False"/>
            <Op id="DVEAndFlyKeyXPosition" mixEffectBlockIndex="0" keyIndex="0" xPosition="0"/>
            <Op id="DVEAndFlyKeyYPosition" mixEffectBlockIndex="0" keyIndex="0" yPosition="-3.2"/>
            <Op id="DVEAndFlyKeyXSize" mixEffectBlockIndex="0" keyIndex="0" xSize="0.649994"/>
            <Op id="DVEAndFlyKeyYSize" mixEffectBlockIndex="0" keyIndex="0" ySize="0.649994"/>
            <Op id="MacroSleep" frames="1"/>
            <Op id="KeyOnAir" mixEffectBlockIndex="0" keyIndex="0" onAir="True"/>
        </Macro>
        <Macro index="1" name="Overlay Off" description="">
            <Op id="KeyOnAir" mixEffectBlockIndex="0" keyIndex="0" onAir="False"/>
        </Macro>
        <Macro index="2" name="Song Over dark" description="Song over with dark transparent panel behind. Must have grey.png in Media Player">
            <Op id="KeyType" mixEffectBlockIndex="0" keyIndex="0" type="Luma"/>
            <Op id="KeyFillInput" mixEffectBlockIndex="0" keyIndex="0" input="Camera4"/>
            <Op id="KeyCutInput" mixEffectBlockIndex="0" keyIndex="0" input="MediaPlayer1"/>
            <Op id="LumaKeyPreMultiply" mixEffectBlockIndex="0" keyIndex="0" preMultiply="True"/>
            <Op id="DVEKeyMaskEnable" mixEffectBlockIndex="0" keyIndex="0" enable="False"/>
            <Op id="DVEAndFlyKeyXPosition" mixEffectBlockIndex="0" keyIndex="0" xPosition="0"/>
            <Op id="DVEAndFlyKeyYPosition" mixEffectBlockIndex="0" keyIndex="0" yPosition="-3.2"/>
            <Op id="DVEAndFlyKeyXSize" mixEffectBlockIndex="0" keyIndex="0" xSize="0.649994"/>
            <Op id="DVEAndFlyKeyYSize" mixEffectBlockIndex="0" keyIndex="0" ySize="0.649994"/>
            <Op id="MacroSleep" frames="1"/>
            <Op id="KeyOnAir" mixEffectBlockIndex="0" keyIndex="0" onAir="True"/>
        </Macro>
        <Macro index="4" name="Top Left DP 35%" description="">
            <Op id="KeyType" mixEffectBlockIndex="0" keyIndex="0" type="DVE"/>
            <Op id="KeyFillInput" mixEffectBlockIndex="0" keyIndex="0" input="Camera4"/>
            <Op id="DVEKeyMaskEnable" mixEffectBlockIndex="0" keyIndex="0" enable="False"/>
            <Op id="DVEKeyBorderEnable" mixEffectBlockIndex="0" keyIndex="0" enable="False"/>
            <Op id="DVEAndFlyKeyXPosition" mixEffectBlockIndex="0" keyIndex="0" xPosition="-10.4"/>
            <Op id="DVEAndFlyKeyYPosition" mixEffectBlockIndex="0" keyIndex="0" yPosition="5.85"/>
            <Op id="DVEAndFlyKeyXSize" mixEffectBlockIndex="0" keyIndex="0" xSize="0.350006"/>
            <Op id="DVEAndFlyKeyYSize" mixEffectBlockIndex="0" keyIndex="0" ySize="0.350006"/>
            <Op id="MacroSleep" frames="1"/>
            <Op id="KeyOnAir" mixEffectBlockIndex="0" keyIndex="0" onAir="True"/>
        </Macro>
        <Macro index="5" name="Top Right DP 35%" description="">
            <Op id="KeyType" mixEffectBlockIndex="0" keyIndex="0" type="DVE"/>
            <Op id="KeyFillInput" mixEffectBlockIndex="0" keyIndex="0" input="Camera4"/>
            <Op id="DVEKeyMaskEnable" mixEffectBlockIndex="0" keyIndex="0" enable="False"/>
            <Op id="DVEKeyBorderEnable" mixEffectBlockIndex="0" keyIndex="0" enable="False"/>
            <Op id="DVEAndFlyKeyXPosition" mixEffectBlockIndex="0" keyIndex="0" xPosition="10.4"/>
            <Op id="DVEAndFlyKeyYPosition" mixEffectBlockIndex="0" keyIndex="0" yPosition="5.85"/>
            <Op id="DVEAndFlyKeyXSize" mixEffectBlockIndex="0" keyIndex="0" xSize="0.350006"/>
            <Op id="DVEAndFlyKeyYSize" mixEffectBlockIndex="0" keyIndex="0" ySize="0.350006"/>
            <Op id="MacroSleep" frames="1"/>
            <Op id="KeyOnAir" mixEffectBlockIndex="0" keyIndex="0" onAir="True"/>
        </Macro>
        <Macro index="6" name="Bot Left DP 35%" description="">
            <Op id="KeyType" mixEffectBlockIndex="0" keyIndex="0" type="DVE"/>
            <Op id="KeyFillInput" mixEffectBlockIndex="0" keyIndex="0" input="Camera4"/>
            <Op id="DVEKeyMaskEnable" mixEffectBlockIndex="0" keyIndex="0" enable="False"/>
            <Op id="DVEKeyBorderEnable" mixEffectBlockIndex="0" keyIndex="0" enable="False"/>
            <Op id="DVEAndFlyKeyXPosition" mixEffectBlockIndex="0" keyIndex="0" xPosition="-10.4"/>
            <Op id="DVEAndFlyKeyYPosition" mixEffectBlockIndex="0" keyIndex="0" yPosition="-5.85"/>
            <Op id="DVEAndFlyKeyXSize" mixEffectBlockIndex="0" keyIndex="0" xSize="0.350006"/>
            <Op id="DVEAndFlyKeyYSize" mixEffectBlockIndex="0" keyIndex="0" ySize="0.350006"/>
            <Op id="MacroSleep" frames="1"/>
            <Op id="KeyOnAir" mixEffectBlockIndex="0" keyIndex="0" onAir="True"/>
        </Macro>
        <Macro index="7" name="Bot Right DP 35%" description="">
            <Op id="KeyFillInput" mixEffectBlockIndex="0" keyIndex="0" input="Camera4"/>
            <Op id="DVEKeyMaskEnable" mixEffectBlockIndex="0" keyIndex="0" enable="False"/>
            <Op id="DVEKeyBorderEnable" mixEffectBlockIndex="0" keyIndex="0" enable="False"/>
            <Op id="DVEAndFlyKeyXPosition" mixEffectBlockIndex="0" keyIndex="0" xPosition="10.4"/>
            <Op id="DVEAndFlyKeyYPosition" mixEffectBlockIndex="0" keyIndex="0" yPosition="-5.85"/>
            <Op id="DVEAndFlyKeyXSize" mixEffectBlockIndex="0" keyIndex="0" xSize="0.350006"/>
            <Op id="DVEAndFlyKeyYSize" mixEffectBlockIndex="0" keyIndex="0" ySize="0.350006"/>
            <Op id="MacroSleep" frames="1"/>
            <Op id="KeyOnAir" mixEffectBlockIndex="0" keyIndex="0" onAir="True"/>
        </Macro>
        <Macro index="8" name="Bot Left DP 65%" description="">
            <Op id="KeyFillInput" mixEffectBlockIndex="0" keyIndex="0" input="Camera4"/>
            <Op id="KeyOnAir" mixEffectBlockIndex="0" keyIndex="0" onAir="True"/>
            <Op id="KeyType" mixEffectBlockIndex="0" keyIndex="0" type="DVE"/>
            <Op id="DVEAndFlyKeyXPosition" mixEffectBlockIndex="0" keyIndex="0" xPosition="-5.6"/>
            <Op id="DVEAndFlyKeyYPosition" mixEffectBlockIndex="0" keyIndex="0" yPosition="-3.15"/>
            <Op id="DVEAndFlyKeyXSize" mixEffectBlockIndex="0" keyIndex="0" xSize="0.649994"/>
            <Op id="DVEAndFlyKeyYSize" mixEffectBlockIndex="0" keyIndex="0" ySize="0.649994"/>
            <Op id="MacroSleep" frames="1"/>
            <Op id="KeyOnAir" mixEffectBlockIndex="0" keyIndex="0" onAir="True"/>
        </Macro>
        <Macro index="9" name="Bot Right DP 65%" description="">
            <Op id="KeyFillInput" mixEffectBlockIndex="0" keyIndex="0" input="Camera4"/>
            <Op id="KeyOnAir" mixEffectBlockIndex="0" keyIndex="0" onAir="True"/>
            <Op id="KeyType" mixEffectBlockIndex="0" keyIndex="0" type="DVE"/>
            <Op id="DVEAndFlyKeyXPosition" mixEffectBlockIndex="0" keyIndex="0" xPosition="5.6"/>
            <Op id="DVEAndFlyKeyYPosition" mixEffectBlockIndex="0" keyIndex="0" yPosition="-3.15"/>
            <Op id="DVEAndFlyKeyXSize" mixEffectBlockIndex="0" keyIndex="0" xSize="0.649994"/>
            <Op id="DVEAndFlyKeyYSize" mixEffectBlockIndex="0" keyIndex="0" ySize="0.649994"/>
            <Op id="MacroSleep" frames="1"/>
            <Op id="KeyOnAir" mixEffectBlockIndex="0" keyIndex="0" onAir="True"/>
        </Macro>
        <Macro index="10" name="Bot Left DP 50%" description="">
            <Op id="KeyFillInput" mixEffectBlockIndex="0" keyIndex="0" input="Camera4"/>
            <Op id="KeyOnAir" mixEffectBlockIndex="0" keyIndex="0" onAir="True"/>
            <Op id="KeyType" mixEffectBlockIndex="0" keyIndex="0" type="DVE"/>
            <Op id="DVEAndFlyKeyXPosition" mixEffectBlockIndex="0" keyIndex="0" xPosition="-7.95"/>
            <Op id="DVEAndFlyKeyYPosition" mixEffectBlockIndex="0" keyIndex="0" yPosition="-4.45"/>
            <Op id="DVEAndFlyKeyXSize" mixEffectBlockIndex="0" keyIndex="0" xSize="0.50"/>
            <Op id="DVEAndFlyKeyYSize" mixEffectBlockIndex="0" keyIndex="0" ySize="0.5"/>
            <Op id="MacroSleep" frames="1"/>
            <Op id="KeyOnAir" mixEffectBlockIndex="0" keyIndex="0" onAir="True"/>
        </Macro>
        <Macro index="11" name="Bot Right DP 50%" description="">
            <Op id="KeyFillInput" mixEffectBlockIndex="0" keyIndex="0" input="Camera4"/>
            <Op id="KeyOnAir" mixEffectBlockIndex="0" keyIndex="0" onAir="True"/>
            <Op id="KeyType" mixEffectBlockIndex="0" keyIndex="0" type="DVE"/>
            <Op id="DVEAndFlyKeyXPosition" mixEffectBlockIndex="0" keyIndex="0" xPosition="7.95"/>
            <Op id="DVEAndFlyKeyYPosition" mixEffectBlockIndex="0" keyIndex="0" yPosition="-4.45"/>
            <Op id="DVEAndFlyKeyXSize" mixEffectBlockIndex="0" keyIndex="0" xSize="0.50"/>
            <Op id="DVEAndFlyKeyYSize" mixEffectBlockIndex="0" keyIndex="0" ySize="0.5"/>
            <Op id="MacroSleep" frames="1"/>
            <Op id="KeyOnAir" mixEffectBlockIndex="0" keyIndex="0" onAir="True"/>
        </Macro>
        <Macro index="12" name="Top Left Cam1 35%" description="">
            <Op id="KeyType" mixEffectBlockIndex="0" keyIndex="0" type="DVE"/>
            <Op id="KeyFillInput" mixEffectBlockIndex="0" keyIndex="0" input="Camera1"/>
            <Op id="DVEKeyMaskEnable" mixEffectBlockIndex="0" keyIndex="0" enable="False"/>
            <Op id="DVEKeyBorderEnable" mixEffectBlockIndex="0" keyIndex="0" enable="False"/>
            <Op id="DVEAndFlyKeyXPosition" mixEffectBlockIndex="0" keyIndex="0" xPosition="-11"/>
            <Op id="DVEAndFlyKeyYPosition" mixEffectBlockIndex="0" keyIndex="0" yPosition="6"/>
            <Op id="DVEAndFlyKeyXSize" mixEffectBlockIndex="0" keyIndex="0" xSize="0.350006"/>
            <Op id="DVEAndFlyKeyYSize" mixEffectBlockIndex="0" keyIndex="0" ySize="0.350006"/>
            <Op id="MacroSleep" frames="1"/>
            <Op id="KeyOnAir" mixEffectBlockIndex="0" keyIndex="0" onAir="True"/>
        </Macro>
        <Macro index="13" name="Top Right Cam1 35%" description="">
            <Op id="KeyType" mixEffectBlockIndex="0" keyIndex="0" type="DVE"/>
            <Op id="KeyFillInput" mixEffectBlockIndex="0" keyIndex="0" input="Camera1"/>
            <Op id="DVEKeyMaskEnable" mixEffectBlockIndex="0" keyIndex="0" enable="False"/>
            <Op id="DVEKeyBorderEnable" mixEffectBlockIndex="0" keyIndex="0" enable="False"/>
            <Op id="DVEAndFlyKeyXPosition" mixEffectBlockIndex="0" keyIndex="0" xPosition="11"/>
            <Op id="DVEAndFlyKeyYPosition" mixEffectBlockIndex="0" keyIndex="0" yPosition="6"/>
            <Op id="DVEAndFlyKeyXSize" mixEffectBlockIndex="0" keyIndex="0" xSize="0.350006"/>
            <Op id="DVEAndFlyKeyYSize" mixEffectBlockIndex="0" keyIndex="0" ySize="0.350006"/>
            <Op id="MacroSleep" frames="1"/>
            <Op id="KeyOnAir" mixEffectBlockIndex="0" keyIndex="0" onAir="True"/>
        </Macro>
        <Macro index="14" name="Bot Left Cam1 35%" description="">
            <Op id="KeyType" mixEffectBlockIndex="0" keyIndex="0" type="DVE"/>
            <Op id="KeyFillInput" mixEffectBlockIndex="0" keyIndex="0" input="Camera1"/>
            <Op id="DVEKeyMaskEnable" mixEffectBlockIndex="0" keyIndex="0" enable="False"/>
            <Op id="DVEKeyBorderEnable" mixEffectBlockIndex="0" keyIndex="0" enable="False"/>
            <Op id="DVEAndFlyKeyXPosition" mixEffectBlockIndex="0" keyIndex="0" xPosition="-11"/>
            <Op id="DVEAndFlyKeyYPosition" mixEffectBlockIndex="0" keyIndex="0" yPosition="-6.00002"/>
            <Op id="DVEAndFlyKeyXSize" mixEffectBlockIndex="0" keyIndex="0" xSize="0.350006"/>
            <Op id="DVEAndFlyKeyYSize" mixEffectBlockIndex="0" keyIndex="0" ySize="0.350006"/>
            <Op id="MacroSleep" frames="1"/>
            <Op id="KeyOnAir" mixEffectBlockIndex="0" keyIndex="0" onAir="True"/>
        </Macro>
        <Macro index="15" name="Bot Right Cam1 35%" description="">
            <Op id="KeyFillInput" mixEffectBlockIndex="0" keyIndex="0" input="Camera1"/>
            <Op id="DVEKeyMaskEnable" mixEffectBlockIndex="0" keyIndex="0" enable="False"/>
            <Op id="DVEKeyBorderEnable" mixEffectBlockIndex="0" keyIndex="0" enable="False"/>
            <Op id="DVEAndFlyKeyXPosition" mixEffectBlockIndex="0" keyIndex="0" xPosition="11"/>
            <Op id="DVEAndFlyKeyYPosition" mixEffectBlockIndex="0" keyIndex="0" yPosition="-6.00002"/>
            <Op id="DVEAndFlyKeyXSize" mixEffectBlockIndex="0" keyIndex="0" xSize="0.350006"/>
            <Op id="DVEAndFlyKeyYSize" mixEffectBlockIndex="0" keyIndex="0" ySize="0.350006"/>
            <Op id="MacroSleep" frames="1"/>
            <Op id="KeyOnAir" mixEffectBlockIndex="0" keyIndex="0" onAir="True"/>
        </Macro>
        <Macro index="18" name="ZoomInCam1" description="">
            <Op id="KeyFillInput" mixEffectBlockIndex="0" keyIndex="0" input="Camera1"/>
            <Op id="KeyType" mixEffectBlockIndex="0" keyIndex="0" type="DVE"/>
            <Op id="DVEAndFlyKeyXPosition" mixEffectBlockIndex="0" keyIndex="0" xPosition="0"/>
            <Op id="DVEAndFlyKeyYPosition" mixEffectBlockIndex="0" keyIndex="0" yPosition="0"/>
            <Op id="DVEAndFlyKeyXSize" mixEffectBlockIndex="0" keyIndex="0" xSize="1"/>
            <Op id="DVEAndFlyKeyYSize" mixEffectBlockIndex="0" keyIndex="0" ySize="1"/>
            <Op id="MacroSleep" frames="1"/>
            <Op id="DVEAndFlyKeyXSize" mixEffectBlockIndex="0" keyIndex="0" xSize="1.6"/>
            <Op id="DVEAndFlyKeyYSize" mixEffectBlockIndex="0" keyIndex="0" ySize="1.6"/>
            <Op id="KeyOnAir" mixEffectBlockIndex="0" keyIndex="0" onAir="True"/>
        </Macro>
        <Macro index="19" name="ZoomInCam2" description="">
            <Op id="KeyFillInput" mixEffectBlockIndex="0" keyIndex="0" input="Camera2"/>
            <Op id="KeyType" mixEffectBlockIndex="0" keyIndex="0" type="DVE"/>
            <Op id="DVEAndFlyKeyXPosition" mixEffectBlockIndex="0" keyIndex="0" xPosition="0"/>
            <Op id="DVEAndFlyKeyYPosition" mixEffectBlockIndex="0" keyIndex="0" yPosition="0"/>
            <Op id="DVEAndFlyKeyXSize" mixEffectBlockIndex="0" keyIndex="0" xSize="1"/>
            <Op id="DVEAndFlyKeyYSize" mixEffectBlockIndex="0" keyIndex="0" ySize="1"/>
            <Op id="MacroSleep" frames="1"/>
            <Op id="DVEAndFlyKeyXSize" mixEffectBlockIndex="0" keyIndex="0" xSize="1.60001"/>
            <Op id="DVEAndFlyKeyYSize" mixEffectBlockIndex="0" keyIndex="0" ySize="1.60001"/>
            <Op id="KeyOnAir" mixEffectBlockIndex="0" keyIndex="0" onAir="True"/>
        </Macro>
                <Macro index="20" name="Song Over 65%" description="">
            <Op id="KeyType" mixEffectBlockIndex="0" keyIndex="0" type="Luma"/>
            <Op id="KeyFillInput" mixEffectBlockIndex="0" keyIndex="0" input="4"/>
            <Op id="KeyCutInput" mixEffectBlockIndex="0" keyIndex="0" input="Black"/>
            <Op id="LumaKeyPreMultiply" mixEffectBlockIndex="0" keyIndex="0" preMultiply="True"/>
            <Op id="DVEKeyMaskEnable" mixEffectBlockIndex="0" keyIndex="0" enable="False"/>
            <Op id="DVEAndFlyKeyXPosition" mixEffectBlockIndex="0" keyIndex="0" xPosition="0"/>
            <Op id="DVEAndFlyKeyYPosition" mixEffectBlockIndex="0" keyIndex="0" yPosition="-3.15"/>
            <Op id="DVEAndFlyKeyXSize" mixEffectBlockIndex="0" keyIndex="0" xSize="0.65"/>
            <Op id="DVEAndFlyKeyYSize" mixEffectBlockIndex="0" keyIndex="0" ySize="0.65"/>
            <Op id="MacroSleep" frames="1"/>
            <Op id="KeyOnAir" mixEffectBlockIndex="0" keyIndex="0" onAir="True"/>
        </Macro>
        <Macro index="21" name="Overlay Off" description="">
            <Op id="KeyOnAir" mixEffectBlockIndex="0" keyIndex="0" onAir="False"/>
        </Macro>
        <Macro index="22" name="Song Over Cam4 65%" description="">
            <Op id="KeyType" mixEffectBlockIndex="0" keyIndex="0" type="Luma"/>
            <Op id="KeyFillInput" mixEffectBlockIndex="0" keyIndex="0" input="4"/>
            <Op id="KeyCutInput" mixEffectBlockIndex="0" keyIndex="0" input="MediaPlayer1"/>
            <Op id="LumaKeyPreMultiply" mixEffectBlockIndex="0" keyIndex="0" preMultiply="True"/>
            <Op id="DVEKeyMaskEnable" mixEffectBlockIndex="0" keyIndex="0" enable="False"/>
            <Op id="DVEAndFlyKeyXPosition" mixEffectBlockIndex="0" keyIndex="0" xPosition="0"/>
            <Op id="DVEAndFlyKeyYPosition" mixEffectBlockIndex="0" keyIndex="0" yPosition="-3.15"/>
            <Op id="DVEAndFlyKeyXSize" mixEffectBlockIndex="0" keyIndex="0" xSize="0.65"/>
            <Op id="DVEAndFlyKeyYSize" mixEffectBlockIndex="0" keyIndex="0" ySize="0.65"/>
            <Op id="MacroSleep" frames="1"/>
            <Op id="KeyOnAir" mixEffectBlockIndex="0" keyIndex="0" onAir="True"/>
        </Macro>
        <Macro index="23" name="Song Over Cam4 60%" description="">
            <Op id="KeyType" mixEffectBlockIndex="0" keyIndex="0" type="Luma"/>
            <Op id="KeyFillInput" mixEffectBlockIndex="0" keyIndex="0" input="4"/>
            <Op id="KeyCutInput" mixEffectBlockIndex="0" keyIndex="0" input="MediaPlayer1"/>
            <Op id="LumaKeyPreMultiply" mixEffectBlockIndex="0" keyIndex="0" preMultiply="True"/>
            <Op id="DVEKeyMaskEnable" mixEffectBlockIndex="0" keyIndex="0" enable="False"/>
            <Op id="DVEAndFlyKeyXPosition" mixEffectBlockIndex="0" keyIndex="0" xPosition="0"/>
            <Op id="DVEAndFlyKeyYPosition" mixEffectBlockIndex="0" keyIndex="0" yPosition="-3.6"/>
            <Op id="DVEAndFlyKeyXSize" mixEffectBlockIndex="0" keyIndex="0" xSize="0.60"/>
            <Op id="DVEAndFlyKeyYSize" mixEffectBlockIndex="0" keyIndex="0" ySize="0.60"/>
            <Op id="MacroSleep" frames="1"/>
            <Op id="KeyOnAir" mixEffectBlockIndex="0" keyIndex="0" onAir="True"/>
        </Macro>
        <Macro index="24" name="Song Over Cam4 55%" description="">
            <Op id="KeyType" mixEffectBlockIndex="0" keyIndex="0" type="Luma"/>
            <Op id="KeyFillInput" mixEffectBlockIndex="0" keyIndex="0" input="4"/>
            <Op id="KeyCutInput" mixEffectBlockIndex="0" keyIndex="0" input="MediaPlayer1"/>
            <Op id="LumaKeyPreMultiply" mixEffectBlockIndex="0" keyIndex="0" preMultiply="True"/>
            <Op id="DVEKeyMaskEnable" mixEffectBlockIndex="0" keyIndex="0" enable="False"/>
            <Op id="DVEAndFlyKeyXPosition" mixEffectBlockIndex="0" keyIndex="0" xPosition="0"/>
            <Op id="DVEAndFlyKeyYPosition" mixEffectBlockIndex="0" keyIndex="0" yPosition="-4.05"/>
            <Op id="DVEAndFlyKeyXSize" mixEffectBlockIndex="0" keyIndex="0" xSize="0.55"/>
            <Op id="DVEAndFlyKeyYSize" mixEffectBlockIndex="0" keyIndex="0" ySize="0.55"/>
            <Op id="MacroSleep" frames="1"/>
            <Op id="KeyOnAir" mixEffectBlockIndex="0" keyIndex="0" onAir="True"/>
        </Macro>
        <Macro index="26" name="Bot Left Cam4 65%" description="">
            <Op id="KeyType" mixEffectBlockIndex="0" keyIndex="0" type="DVE"/>
            <Op id="KeyFillInput" mixEffectBlockIndex="0" keyIndex="0" input="4"/>
            <Op id="DVEKeyMaskEnable" mixEffectBlockIndex="0" keyIndex="0" enable="False"/>
            <Op id="DVEKeyMaskEnable" mixEffectBlockIndex="0" keyIndex="0" enable="False"/>
            <Op id="DVEKeyBorderEnable" mixEffectBlockIndex="0" keyIndex="0" enable="False"/>
            <Op id="DVEAndFlyKeyXPosition" mixEffectBlockIndex="0" keyIndex="0" xPosition="-5.6"/>
            <Op id="DVEAndFlyKeyYPosition" mixEffectBlockIndex="0" keyIndex="0" yPosition="-3.15"/>
            <Op id="DVEAndFlyKeyXSize" mixEffectBlockIndex="0" keyIndex="0" xSize="0.65"/>
            <Op id="DVEAndFlyKeyYSize" mixEffectBlockIndex="0" keyIndex="0" ySize="0.65"/>
            <Op id="MacroSleep" frames="1"/>
            <Op id="KeyOnAir" mixEffectBlockIndex="0" keyIndex="0" onAir="True"/>
        </Macro>
        <Macro index="27" name="Bot Left Cam4 60%" description="">
            <Op id="KeyType" mixEffectBlockIndex="0" keyIndex="0" type="DVE"/>
            <Op id="KeyFillInput" mixEffectBlockIndex="0" keyIndex="0" input="4"/>
            <Op id="DVEKeyMaskEnable" mixEffectBlockIndex="0" keyIndex="0" enable="False"/>
            <Op id="DVEKeyMaskEnable" mixEffectBlockIndex="0" keyIndex="0" enable="False"/>
            <Op id="DVEKeyBorderEnable" mixEffectBlockIndex="0" keyIndex="0" enable="False"/>
            <Op id="DVEAndFlyKeyXPosition" mixEffectBlockIndex="0" keyIndex="0" xPosition="-6.4"/>
            <Op id="DVEAndFlyKeyYPosition" mixEffectBlockIndex="0" keyIndex="0" yPosition="-3.6"/>
            <Op id="DVEAndFlyKeyXSize" mixEffectBlockIndex="0" keyIndex="0" xSize="0.60"/>
            <Op id="DVEAndFlyKeyYSize" mixEffectBlockIndex="0" keyIndex="0" ySize="0.60"/>
            <Op id="MacroSleep" frames="1"/>
            <Op id="KeyOnAir" mixEffectBlockIndex="0" keyIndex="0" onAir="True"/>
        </Macro>
        <Macro index="28" name="Bot Left Cam4 55%" description="">
            <Op id="KeyType" mixEffectBlockIndex="0" keyIndex="0" type="DVE"/>
            <Op id="KeyFillInput" mixEffectBlockIndex="0" keyIndex="0" input="4"/>
            <Op id="DVEKeyMaskEnable" mixEffectBlockIndex="0" keyIndex="0" enable="False"/>
            <Op id="DVEKeyMaskEnable" mixEffectBlockIndex="0" keyIndex="0" enable="False"/>
            <Op id="DVEKeyBorderEnable" mixEffectBlockIndex="0" keyIndex="0" enable="False"/>
            <Op id="DVEAndFlyKeyXPosition" mixEffectBlockIndex="0" keyIndex="0" xPosition="-7.2"/>
            <Op id="DVEAndFlyKeyYPosition" mixEffectBlockIndex="0" keyIndex="0" yPosition="-4.05"/>
            <Op id="DVEAndFlyKeyXSize" mixEffectBlockIndex="0" keyIndex="0" xSize="0.55"/>
            <Op id="DVEAndFlyKeyYSize" mixEffectBlockIndex="0" keyIndex="0" ySize="0.55"/>
            <Op id="MacroSleep" frames="1"/>
            <Op id="KeyOnAir" mixEffectBlockIndex="0" keyIndex="0" onAir="True"/>
        </Macro>
        <Macro index="29" name="Bot Left Cam4 50%" description="">
            <Op id="KeyType" mixEffectBlockIndex="0" keyIndex="0" type="DVE"/>
            <Op id="KeyFillInput" mixEffectBlockIndex="0" keyIndex="0" input="4"/>
            <Op id="DVEKeyMaskEnable" mixEffectBlockIndex="0" keyIndex="0" enable="False"/>
            <Op id="DVEKeyMaskEnable" mixEffectBlockIndex="0" keyIndex="0" enable="False"/>
            <Op id="DVEKeyBorderEnable" mixEffectBlockIndex="0" keyIndex="0" enable="False"/>
            <Op id="DVEAndFlyKeyXPosition" mixEffectBlockIndex="0" keyIndex="0" xPosition="-8"/>
            <Op id="DVEAndFlyKeyYPosition" mixEffectBlockIndex="0" keyIndex="0" yPosition="-4.5"/>
            <Op id="DVEAndFlyKeyXSize" mixEffectBlockIndex="0" keyIndex="0" xSize="0.50"/>
            <Op id="DVEAndFlyKeyYSize" mixEffectBlockIndex="0" keyIndex="0" ySize="0.50"/>
            <Op id="MacroSleep" frames="1"/>
            <Op id="KeyOnAir" mixEffectBlockIndex="0" keyIndex="0" onAir="True"/>
        </Macro>
        <Macro index="30" name="Bot Right Cam4 55%" description="">
            <Op id="KeyType" mixEffectBlockIndex="0" keyIndex="0" type="DVE"/>
            <Op id="KeyFillInput" mixEffectBlockIndex="0" keyIndex="0" input="4"/>
            <Op id="DVEKeyMaskEnable" mixEffectBlockIndex="0" keyIndex="0" enable="False"/>
            <Op id="DVEKeyMaskEnable" mixEffectBlockIndex="0" keyIndex="0" enable="False"/>
            <Op id="DVEKeyBorderEnable" mixEffectBlockIndex="0" keyIndex="0" enable="False"/>
            <Op id="DVEAndFlyKeyXPosition" mixEffectBlockIndex="0" keyIndex="0" xPosition="7.2"/>
            <Op id="DVEAndFlyKeyYPosition" mixEffectBlockIndex="0" keyIndex="0" yPosition="-4.05"/>
            <Op id="DVEAndFlyKeyXSize" mixEffectBlockIndex="0" keyIndex="0" xSize="0.55"/>
            <Op id="DVEAndFlyKeyYSize" mixEffectBlockIndex="0" keyIndex="0" ySize="0.55"/>
            <Op id="MacroSleep" frames="1"/>
            <Op id="KeyOnAir" mixEffectBlockIndex="0" keyIndex="0" onAir="True"/>
        </Macro>
        <Macro index="32" name="Top Left Cam1 25%" description="">
            <Op id="KeyType" mixEffectBlockIndex="0" keyIndex="0" type="DVE"/>
            <Op id="KeyFillInput" mixEffectBlockIndex="0" keyIndex="0" input="1"/>
            <Op id="DVEKeyMaskEnable" mixEffectBlockIndex="0" keyIndex="0" enable="False"/>
            <Op id="DVEKeyMaskEnable" mixEffectBlockIndex="0" keyIndex="0" enable="False"/>
            <Op id="DVEKeyBorderEnable" mixEffectBlockIndex="0" keyIndex="0" enable="False"/>
            <Op id="DVEAndFlyKeyXPosition" mixEffectBlockIndex="0" keyIndex="0" xPosition="-12"/>
            <Op id="DVEAndFlyKeyYPosition" mixEffectBlockIndex="0" keyIndex="0" yPosition="6.75"/>
            <Op id="DVEAndFlyKeyXSize" mixEffectBlockIndex="0" keyIndex="0" xSize="0.25"/>
            <Op id="DVEAndFlyKeyYSize" mixEffectBlockIndex="0" keyIndex="0" ySize="0.25"/>
            <Op id="MacroSleep" frames="1"/>
            <Op id="KeyOnAir" mixEffectBlockIndex="0" keyIndex="0" onAir="True"/>
        </Macro>
        <Macro index="33" name="Top Right Cam1 25%" description="">
            <Op id="KeyType" mixEffectBlockIndex="0" keyIndex="0" type="DVE"/>
            <Op id="KeyFillInput" mixEffectBlockIndex="0" keyIndex="0" input="1"/>
            <Op id="DVEKeyMaskEnable" mixEffectBlockIndex="0" keyIndex="0" enable="False"/>
            <Op id="DVEKeyMaskEnable" mixEffectBlockIndex="0" keyIndex="0" enable="False"/>
            <Op id="DVEKeyBorderEnable" mixEffectBlockIndex="0" keyIndex="0" enable="False"/>
            <Op id="DVEAndFlyKeyXPosition" mixEffectBlockIndex="0" keyIndex="0" xPosition="12"/>
            <Op id="DVEAndFlyKeyYPosition" mixEffectBlockIndex="0" keyIndex="0" yPosition="6.75"/>
            <Op id="DVEAndFlyKeyXSize" mixEffectBlockIndex="0" keyIndex="0" xSize="0.25"/>
            <Op id="DVEAndFlyKeyYSize" mixEffectBlockIndex="0" keyIndex="0" ySize="0.25"/>
            <Op id="MacroSleep" frames="1"/>
            <Op id="KeyOnAir" mixEffectBlockIndex="0" keyIndex="0" onAir="True"/>
        </Macro>
        <Macro index="34" name="Bot Left Cam1 25%" description="">
            <Op id="KeyType" mixEffectBlockIndex="0" keyIndex="0" type="DVE"/>
            <Op id="KeyFillInput" mixEffectBlockIndex="0" keyIndex="0" input="1"/>
            <Op id="DVEKeyMaskEnable" mixEffectBlockIndex="0" keyIndex="0" enable="False"/>
            <Op id="DVEKeyMaskEnable" mixEffectBlockIndex="0" keyIndex="0" enable="False"/>
            <Op id="DVEKeyBorderEnable" mixEffectBlockIndex="0" keyIndex="0" enable="False"/>
            <Op id="DVEAndFlyKeyXPosition" mixEffectBlockIndex="0" keyIndex="0" xPosition="-12"/>
            <Op id="DVEAndFlyKeyYPosition" mixEffectBlockIndex="0" keyIndex="0" yPosition="-6.75"/>
            <Op id="DVEAndFlyKeyXSize" mixEffectBlockIndex="0" keyIndex="0" xSize="0.25"/>
            <Op id="DVEAndFlyKeyYSize" mixEffectBlockIndex="0" keyIndex="0" ySize="0.25"/>
            <Op id="MacroSleep" frames="1"/>
            <Op id="KeyOnAir" mixEffectBlockIndex="0" keyIndex="0" onAir="True"/>
        </Macro>
        <Macro index="35" name="Bot Right Cam1 25%" description="">
            <Op id="KeyType" mixEffectBlockIndex="0" keyIndex="0" type="DVE"/>
            <Op id="KeyFillInput" mixEffectBlockIndex="0" keyIndex="0" input="1"/>
            <Op id="DVEKeyMaskEnable" mixEffectBlockIndex="0" keyIndex="0" enable="False"/>
            <Op id="DVEKeyMaskEnable" mixEffectBlockIndex="0" keyIndex="0" enable="False"/>
            <Op id="DVEKeyBorderEnable" mixEffectBlockIndex="0" keyIndex="0" enable="False"/>
            <Op id="DVEAndFlyKeyXPosition" mixEffectBlockIndex="0" keyIndex="0" xPosition="12"/>
            <Op id="DVEAndFlyKeyYPosition" mixEffectBlockIndex="0" keyIndex="0" yPosition="-6.75"/>
            <Op id="DVEAndFlyKeyXSize" mixEffectBlockIndex="0" keyIndex="0" xSize="0.25"/>
            <Op id="DVEAndFlyKeyYSize" mixEffectBlockIndex="0" keyIndex="0" ySize="0.25"/>
            <Op id="MacroSleep" frames="1"/>
            <Op id="KeyOnAir" mixEffectBlockIndex="0" keyIndex="0" onAir="True"/>
        </Macro>
        <Macro index="36" name="Top Left Cam1 35%" description="">
            <Op id="KeyType" mixEffectBlockIndex="0" keyIndex="0" type="DVE"/>
            <Op id="KeyFillInput" mixEffectBlockIndex="0" keyIndex="0" input="1"/>
            <Op id="DVEKeyMaskEnable" mixEffectBlockIndex="0" keyIndex="0" enable="False"/>
            <Op id="DVEKeyMaskEnable" mixEffectBlockIndex="0" keyIndex="0" enable="False"/>
            <Op id="DVEKeyBorderEnable" mixEffectBlockIndex="0" keyIndex="0" enable="False"/>
            <Op id="DVEAndFlyKeyXPosition" mixEffectBlockIndex="0" keyIndex="0" xPosition="-10.4"/>
            <Op id="DVEAndFlyKeyYPosition" mixEffectBlockIndex="0" keyIndex="0" yPosition="5.85"/>
            <Op id="DVEAndFlyKeyXSize" mixEffectBlockIndex="0" keyIndex="0" xSize="0.35"/>
            <Op id="DVEAndFlyKeyYSize" mixEffectBlockIndex="0" keyIndex="0" ySize="0.35"/>
            <Op id="MacroSleep" frames="1"/>
            <Op id="KeyOnAir" mixEffectBlockIndex="0" keyIndex="0" onAir="True"/>
        </Macro>
        <Macro index="37" name="Top Right Cam1 35%" description="">
            <Op id="KeyType" mixEffectBlockIndex="0" keyIndex="0" type="DVE"/>
            <Op id="KeyFillInput" mixEffectBlockIndex="0" keyIndex="0" input="1"/>
            <Op id="DVEKeyMaskEnable" mixEffectBlockIndex="0" keyIndex="0" enable="False"/>
            <Op id="DVEKeyMaskEnable" mixEffectBlockIndex="0" keyIndex="0" enable="False"/>
            <Op id="DVEKeyBorderEnable" mixEffectBlockIndex="0" keyIndex="0" enable="False"/>
            <Op id="DVEAndFlyKeyXPosition" mixEffectBlockIndex="0" keyIndex="0" xPosition="10.4"/>
            <Op id="DVEAndFlyKeyYPosition" mixEffectBlockIndex="0" keyIndex="0" yPosition="5.85"/>
            <Op id="DVEAndFlyKeyXSize" mixEffectBlockIndex="0" keyIndex="0" xSize="0.35"/>
            <Op id="DVEAndFlyKeyYSize" mixEffectBlockIndex="0" keyIndex="0" ySize="0.35"/>
            <Op id="MacroSleep" frames="1"/>
            <Op id="KeyOnAir" mixEffectBlockIndex="0" keyIndex="0" onAir="True"/>
        </Macro>
        <Macro index="38" name="Bot Left Cam1 35%" description="">
            <Op id="KeyType" mixEffectBlockIndex="0" keyIndex="0" type="DVE"/>
            <Op id="KeyFillInput" mixEffectBlockIndex="0" keyIndex="0" input="1"/>
            <Op id="DVEKeyMaskEnable" mixEffectBlockIndex="0" keyIndex="0" enable="False"/>
            <Op id="DVEKeyMaskEnable" mixEffectBlockIndex="0" keyIndex="0" enable="False"/>
            <Op id="DVEKeyBorderEnable" mixEffectBlockIndex="0" keyIndex="0" enable="False"/>
            <Op id="DVEAndFlyKeyXPosition" mixEffectBlockIndex="0" keyIndex="0" xPosition="-10.4"/>
            <Op id="DVEAndFlyKeyYPosition" mixEffectBlockIndex="0" keyIndex="0" yPosition="-5.85"/>
            <Op id="DVEAndFlyKeyXSize" mixEffectBlockIndex="0" keyIndex="0" xSize="0.35"/>
            <Op id="DVEAndFlyKeyYSize" mixEffectBlockIndex="0" keyIndex="0" ySize="0.35"/>
            <Op id="MacroSleep" frames="1"/>
            <Op id="KeyOnAir" mixEffectBlockIndex="0" keyIndex="0" onAir="True"/>
        </Macro>
        <Macro index="39" name="Bot Right Cam1 35%" description="">
            <Op id="KeyType" mixEffectBlockIndex="0" keyIndex="0" type="DVE"/>
            <Op id="KeyFillInput" mixEffectBlockIndex="0" keyIndex="0" input="1"/>
            <Op id="DVEKeyMaskEnable" mixEffectBlockIndex="0" keyIndex="0" enable="False"/>
            <Op id="DVEKeyMaskEnable" mixEffectBlockIndex="0" keyIndex="0" enable="False"/>
            <Op id="DVEKeyBorderEnable" mixEffectBlockIndex="0" keyIndex="0" enable="False"/>
            <Op id="DVEAndFlyKeyXPosition" mixEffectBlockIndex="0" keyIndex="0" xPosition="10.4"/>
            <Op id="DVEAndFlyKeyYPosition" mixEffectBlockIndex="0" keyIndex="0" yPosition="-5.85"/>
            <Op id="DVEAndFlyKeyXSize" mixEffectBlockIndex="0" keyIndex="0" xSize="0.35"/>
            <Op id="DVEAndFlyKeyYSize" mixEffectBlockIndex="0" keyIndex="0" ySize="0.35"/>
            <Op id="MacroSleep" frames="1"/>
            <Op id="KeyOnAir" mixEffectBlockIndex="0" keyIndex="0" onAir="True"/>
        </Macro>
        <Macro index="41" name="Overlay Off" description="">
            <Op id="KeyOnAir" mixEffectBlockIndex="0" keyIndex="0" onAir="False"/>
        </Macro>
        <Macro index="42" name="Top Left Cam1 150%" description="">
            <Op id="KeyType" mixEffectBlockIndex="0" keyIndex="0" type="DVE"/>
            <Op id="KeyFillInput" mixEffectBlockIndex="0" keyIndex="0" input="1"/>
            <Op id="DVEKeyMaskEnable" mixEffectBlockIndex="0" keyIndex="0" enable="False"/>
            <Op id="DVEKeyMaskEnable" mixEffectBlockIndex="0" keyIndex="0" enable="False"/>
            <Op id="DVEKeyBorderEnable" mixEffectBlockIndex="0" keyIndex="0" enable="False"/>
            <Op id="DVEAndFlyKeyXPosition" mixEffectBlockIndex="0" keyIndex="0" xPosition="8"/>
            <Op id="DVEAndFlyKeyYPosition" mixEffectBlockIndex="0" keyIndex="0" yPosition="-4.5"/>
            <Op id="DVEAndFlyKeyXSize" mixEffectBlockIndex="0" keyIndex="0" xSize="1.50"/>
            <Op id="DVEAndFlyKeyYSize" mixEffectBlockIndex="0" keyIndex="0" ySize="1.50"/>
            <Op id="MacroSleep" frames="1"/>
            <Op id="KeyOnAir" mixEffectBlockIndex="0" keyIndex="0" onAir="True"/>
        </Macro>
        <Macro index="43" name="Top Right Cam1 150%" description="">
            <Op id="KeyType" mixEffectBlockIndex="0" keyIndex="0" type="DVE"/>
            <Op id="KeyFillInput" mixEffectBlockIndex="0" keyIndex="0" input="1"/>
            <Op id="DVEKeyMaskEnable" mixEffectBlockIndex="0" keyIndex="0" enable="False"/>
            <Op id="DVEKeyMaskEnable" mixEffectBlockIndex="0" keyIndex="0" enable="False"/>
            <Op id="DVEKeyBorderEnable" mixEffectBlockIndex="0" keyIndex="0" enable="False"/>
            <Op id="DVEAndFlyKeyXPosition" mixEffectBlockIndex="0" keyIndex="0" xPosition="-8"/>
            <Op id="DVEAndFlyKeyYPosition" mixEffectBlockIndex="0" keyIndex="0" yPosition="-4.5"/>
            <Op id="DVEAndFlyKeyXSize" mixEffectBlockIndex="0" keyIndex="0" xSize="1.50"/>
            <Op id="DVEAndFlyKeyYSize" mixEffectBlockIndex="0" keyIndex="0" ySize="1.50"/>
            <Op id="MacroSleep" frames="1"/>
            <Op id="KeyOnAir" mixEffectBlockIndex="0" keyIndex="0" onAir="True"/>
        </Macro>
        <Macro index="44" name="Z Top Center Cam1 150%" description="">
            <Op id="KeyType" mixEffectBlockIndex="0" keyIndex="0" type="DVE"/>
            <Op id="KeyFillInput" mixEffectBlockIndex="0" keyIndex="0" input="1"/>
            <Op id="DVEKeyMaskEnable" mixEffectBlockIndex="0" keyIndex="0" enable="False"/>
            <Op id="DVEKeyMaskEnable" mixEffectBlockIndex="0" keyIndex="0" enable="False"/>
            <Op id="DVEKeyBorderEnable" mixEffectBlockIndex="0" keyIndex="0" enable="False"/>
            <Op id="DVEAndFlyKeyXPosition" mixEffectBlockIndex="0" keyIndex="0" xPosition="0"/>
            <Op id="DVEAndFlyKeyYPosition" mixEffectBlockIndex="0" keyIndex="0" yPosition="-4.5"/>
            <Op id="DVEAndFlyKeyXSize" mixEffectBlockIndex="0" keyIndex="0" xSize="1.50"/>
            <Op id="DVEAndFlyKeyYSize" mixEffectBlockIndex="0" keyIndex="0" ySize="1.50"/>
            <Op id="MacroSleep" frames="1"/>
            <Op id="KeyOnAir" mixEffectBlockIndex="0" keyIndex="0" onAir="True"/>
        </Macro>
        <Macro index="46" name="Top Left Cam1 150%" description="">
            <Op id="KeyType" mixEffectBlockIndex="0" keyIndex="0" type="DVE"/>
            <Op id="KeyFillInput" mixEffectBlockIndex="0" keyIndex="0" input="1"/>
            <Op id="DVEKeyMaskEnable" mixEffectBlockIndex="0" keyIndex="0" enable="False"/>
            <Op id="DVEKeyMaskEnable" mixEffectBlockIndex="0" keyIndex="0" enable="False"/>
            <Op id="DVEKeyBorderEnable" mixEffectBlockIndex="0" keyIndex="0" enable="False"/>
            <Op id="DVEAndFlyKeyXPosition" mixEffectBlockIndex="0" keyIndex="0" xPosition="8"/>
            <Op id="DVEAndFlyKeyYPosition" mixEffectBlockIndex="0" keyIndex="0" yPosition="-4.5"/>
            <Op id="DVEAndFlyKeyXSize" mixEffectBlockIndex="0" keyIndex="0" xSize="1.50"/>
            <Op id="DVEAndFlyKeyYSize" mixEffectBlockIndex="0" keyIndex="0" ySize="1.50"/>
            <Op id="MacroSleep" frames="1"/>
            <Op id="KeyOnAir" mixEffectBlockIndex="0" keyIndex="0" onAir="True"/>
        </Macro>
        <Macro index="47" name="Top Right Cam1 150%" description="">
            <Op id="KeyType" mixEffectBlockIndex="0" keyIndex="0" type="DVE"/>
            <Op id="KeyFillInput" mixEffectBlockIndex="0" keyIndex="0" input="1"/>
            <Op id="DVEKeyMaskEnable" mixEffectBlockIndex="0" keyIndex="0" enable="False"/>
            <Op id="DVEKeyMaskEnable" mixEffectBlockIndex="0" keyIndex="0" enable="False"/>
            <Op id="DVEKeyBorderEnable" mixEffectBlockIndex="0" keyIndex="0" enable="False"/>
            <Op id="DVEAndFlyKeyXPosition" mixEffectBlockIndex="0" keyIndex="0" xPosition="-8"/>
            <Op id="DVEAndFlyKeyYPosition" mixEffectBlockIndex="0" keyIndex="0" yPosition="-4.5"/>
            <Op id="DVEAndFlyKeyXSize" mixEffectBlockIndex="0" keyIndex="0" xSize="1.50"/>
            <Op id="DVEAndFlyKeyYSize" mixEffectBlockIndex="0" keyIndex="0" ySize="1.50"/>
            <Op id="MacroSleep" frames="1"/>
            <Op id="KeyOnAir" mixEffectBlockIndex="0" keyIndex="0" onAir="True"/>
        </Macro>
        <Macro index="48" name="Z Top Center Cam1 150%" description="">
            <Op id="KeyType" mixEffectBlockIndex="0" keyIndex="0" type="DVE"/>
            <Op id="KeyFillInput" mixEffectBlockIndex="0" keyIndex="0" input="1"/>
            <Op id="DVEKeyMaskEnable" mixEffectBlockIndex="0" keyIndex="0" enable="False"/>
            <Op id="DVEKeyMaskEnable" mixEffectBlockIndex="0" keyIndex="0" enable="False"/>
            <Op id="DVEKeyBorderEnable" mixEffectBlockIndex="0" keyIndex="0" enable="False"/>
            <Op id="DVEAndFlyKeyXPosition" mixEffectBlockIndex="0" keyIndex="0" xPosition="0"/>
            <Op id="DVEAndFlyKeyYPosition" mixEffectBlockIndex="0" keyIndex="0" yPosition="-4.5"/>
            <Op id="DVEAndFlyKeyXSize" mixEffectBlockIndex="0" keyIndex="0" xSize="1.50"/>
            <Op id="DVEAndFlyKeyYSize" mixEffectBlockIndex="0" keyIndex="0" ySize="1.50"/>
            <Op id="MacroSleep" frames="1"/>
            <Op id="KeyOnAir" mixEffectBlockIndex="0" keyIndex="0" onAir="True"/>
        </Macro>
        <Macro index="80" name="DS song over" description="">
            <Op id="DownstreamKeyMaskLeft" keyIndex="0" left="-16"/>
            <Op id="DownstreamKeyMaskTop" keyIndex="0" top="7.88"/>
            <Op id="DownstreamKeyMaskRight" keyIndex="0" right="16"/>
            <Op id="DownstreamKeyMaskBottom" keyIndex="0" bottom="-9.00002"/>
            <Op id="DownstreamKeyFillInput" keyIndex="0" input="Camera4"/>
            <Op id="DownstreamKeyCutInput" keyIndex="0" input="MediaPlayer1"/>
            <Op id="MacroSleep" frames="1"/>
            <Op id="KeyOnAir" mixEffectBlockIndex="0" keyIndex="0" onAir="True"/>
        </Macro>
    </MacroPool>
    <MacroControl loop="False"/>
</Profile>
